COPYING
INSTALL.txt
MANIFEST.in
README.txt
hwit-edit.iss
setup.py
hwit/__init__.py
hwit/edit/__init__.py
hwit/edit/about.py
hwit/edit/app.py
hwit/edit/editors.py
hwit/edit/main.py
hwit/edit/resources.py
hwit/edit/widgets.py
hwit/edit/doc/Makefile
hwit/edit/doc/__init__.py
hwit/edit/doc/conf.py
hwit/edit/doc/hwit-guide.rst
hwit/edit/doc/hwit-stories.rst
hwit/edit/doc/index.rst
hwit/edit/doc/make.bat
hwit/edit/doc/_static/HWIT_browser-628x480.png
hwit/edit/doc/_static/HWIT_console-480x315.png
hwit/edit/doc/_static/HWIT_editor-683x480.png
hwit/edit/doc/_static/dialog-information-32x32.png
hwit/edit/doc/_static/document-new-32x32.png
hwit/edit/doc/_static/document-open-32x32.png
hwit/edit/doc/_static/document-save-32x32.png
hwit/edit/doc/_static/folder-open-32x32.png
hwit/edit/doc/_static/help-browser-32x32.png
hwit/edit/doc/_static/hwit_collate-200x150.png
hwit/edit/doc/_static/hwit_collate_browse-260x260.png
hwit/edit/doc/_static/hwit_collate_progress-300x110.png
hwit/edit/doc/_static/hwit_icon-96x96.png
hwit/edit/doc/_static/hwit_import-200x150.png
hwit/edit/doc/_static/hwit_mandatory-600x336.png
hwit/edit/doc/_static/hwit_open-200x150.png
hwit/edit/doc/_static/hwit_optional-600x336.png
hwit/edit/doc/_static/hwit_valid-600x336.png
hwit/edit/doc/_static/hwitpqt_editor-600x336.png
hwit/edit/doc/_static/internet-group-chat-32x32.png
hwit/edit/doc/_static/system-log-out-32x32.png
hwit/edit/doc/_static/text-html-32x32.png
hwit/edit/graphics/dialog-information.svg
hwit/edit/graphics/document-new.svg
hwit/edit/graphics/document-open.svg
hwit/edit/graphics/document-save.svg
hwit/edit/graphics/folder-open.svg
hwit/edit/graphics/help-browser.svg
hwit/edit/graphics/internet-group-chat.svg
hwit/edit/graphics/system-log-out.svg
hwit/edit/graphics/text-html.svg
hwit/edit/test/__init__.py
hwit/edit/test/test_widget.py
hwit_edit.egg-info/PKG-INFO
hwit_edit.egg-info/SOURCES.txt
hwit_edit.egg-info/dependency_links.txt
hwit_edit.egg-info/entry_points.txt
hwit_edit.egg-info/namespace_packages.txt
hwit_edit.egg-info/requires.txt
hwit_edit.egg-info/top_level.txt