Metadata-Version: 1.1
Name: hwit-edit
Version: 0.01-r00662
Summary: Here's What I Think; GUI editor
Home-page: http://hwit.org
Author: D Haynes
Author-email: tundish@thuswise.org
License: COPYING
Platform: UNKNOWN
Classifier: Operating System :: OS Independent
Classifier: Programming Language :: Python :: 2.7
Classifier: License :: OSI Approved :: GNU General Public License v3 or later (GPLv3+)
